azst7735/__init__.py
azst7735/st7735.py
az_st7735-0.1.4.dist-info/LICENSE
az_st7735-0.1.4.dist-info/METADATA
az_st7735-0.1.4.dist-info/WHEEL
az_st7735-0.1.4.dist-info/top_level.txt
az_st7735-0.1.4.dist-info/RECORD
